pywanda.cp38-win_amd64.pyd
pywanda-4.6.0.data/data/lib/site-packages/Component64.dll
pywanda-4.6.0.data/data/lib/site-packages/RefPropDll64.dll
pywanda-4.6.0.data/data/lib/site-packages/WandaEngine_native64.dll
pywanda-4.6.0.data/data/lib/site-packages/dauth.dll
pywanda-4.6.0.data/data/lib/site-packages/libifcoremd.dll
pywanda-4.6.0.data/data/lib/site-packages/libifportmd.dll
pywanda-4.6.0.data/data/lib/site-packages/libmmd.dll
pywanda-4.6.0.data/data/lib/site-packages/nefis.dll
pywanda-4.6.0.dist-info/METADATA
pywanda-4.6.0.dist-info/WHEEL
pywanda-4.6.0.dist-info/top_level.txt
pywanda-4.6.0.dist-info/RECORD
