Metadata-Version: 2.1
Name: pywanda
Version: 4.6.0
Summary: Python bindings for the Wanda API
Home-page: https://www.deltares.nl/en/software/wanda/
Author: Michiel Tukker
Author-email: Michiel.Tukker@deltares.nl
License: UNKNOWN
Platform: UNKNOWN
Classifier: Development Status :: 4 - Beta
Classifier: Intended Audience :: Developers
Classifier: Intended Audience :: Science/Research
Classifier: Intended Audience :: Information Technology
Classifier: License :: Other/Proprietary License
Classifier: Programming Language :: Python :: 3
Classifier: Topic :: Scientific/Engineering :: Mathematics
Classifier: Topic :: Scientific/Engineering :: Physics
Classifier: Operating System :: Microsoft :: Windows
Requires-Dist: pybind11 (>=2.2)
